metacall/__init__.py
metacall/api.py
metacall-0.5.3.dist-info/METADATA
metacall-0.5.3.dist-info/WHEEL
metacall-0.5.3.dist-info/top_level.txt
metacall-0.5.3.dist-info/RECORD
