Metadata-Version: 2.4
Name: metacall
Version: 0.5.3
Summary: A library for providing inter-language foreign function interface calls
Home-page: https://github.com/metacall/core
Author: Vicente Eduardo Ferrer Garcia
Author-email: vic798@gmail.com
License: Apache License 2.0
Project-URL: Homepage, https://metacall.io
Project-URL: Repository, https://github.com/metacall/core
Project-URL: Documentation, https://core.metacall.io/
Project-URL: Issues, https://github.com/metacall/core/issues
Keywords: metacall python port ffi polyglot faas serverless
Classifier: Development Status :: 4 - Beta
Classifier: Intended Audience :: Developers
Classifier: Topic :: Software Development :: Interpreters
Classifier: Programming Language :: Python :: 3
Classifier: Programming Language :: Python :: 3.3
Classifier: Programming Language :: Python :: 3.4
Classifier: Programming Language :: Python :: 3.5
Classifier: Programming Language :: Python :: 3.6
Classifier: Programming Language :: Python :: 3.7
Classifier: Programming Language :: Python :: 3.8
Classifier: Programming Language :: Python :: 3.9
Classifier: Programming Language :: Python :: 3.10
Classifier: Programming Language :: Python :: 3.11
Classifier: Programming Language :: Python :: 3.12
Classifier: Programming Language :: Python :: 3.13
Requires-Python: >=3.3
Provides-Extra: dev
Requires-Dist: check-manifest; extra == "dev"
Provides-Extra: test
Requires-Dist: coverage; extra == "test"
Dynamic: author
Dynamic: author-email
Dynamic: classifier
Dynamic: description
Dynamic: description-content-type
Dynamic: home-page
Dynamic: keywords
Dynamic: license
Dynamic: project-url
Dynamic: provides-extra
Dynamic: requires-python
Dynamic: summary
